sasdbpy/__init__.py
sasdbpy/sasdbreader.py
test/__init__.py
test/testSasDbReader.py
sasdbpy-0.0.8.dist-info/METADATA
sasdbpy-0.0.8.dist-info/WHEEL
sasdbpy-0.0.8.dist-info/top_level.txt
sasdbpy-0.0.8.dist-info/RECORD
