Metadata-Version: 2.1
Name: sasdbpy
Version: 0.0.8
Summary: A helper class for reading sas7bdat database files
Home-page: https://github.com/cereddy/sasdbpy
Author: Cereddy
Author-email: nacer.htag@gmail.com
License: UNKNOWN
Project-URL: Bug Tracker, https://github.com/cereddy/sasdbpy/issues
Platform: UNKNOWN
Classifier: Programming Language :: Python :: 3
Classifier: License :: OSI Approved :: MIT License
Classifier: Operating System :: OS Independent
Requires-Python: >=3.6
Requires-Dist: numpy
Requires-Dist: pandas
Requires-Dist: sas7bdat
